redpepper/manager/__init__.py
redpepper/manager/__main__.py
redpepper/manager/apiserver.py
redpepper/manager/config.py
redpepper/manager/data.py
redpepper/manager/entrypoint.py
redpepper/manager/eventlog.py
redpepper/manager/manager.py
redpepper/manager/manager.yml
redpepper_manager-0.3.3.dist-info/METADATA
redpepper_manager-0.3.3.dist-info/WHEEL
redpepper_manager-0.3.3.dist-info/entry_points.txt
redpepper_manager-0.3.3.dist-info/RECORD
